D_Flip_Flop.v
module D_Flip_Flop (
 input clk,
 input rst,
 input data,
 output reg q
);

always @(posedge clk) begin
    if(rst)
     q <= 1'b0;
    else
     q <= data;
end
    
endmodule

D_Flip_Flop_tb.v
`timescale 1ps/1ps
`include "D_Flip_Flop.v"

module D_Flip_Flop_tb();

reg clk;
reg rst;
reg data;
wire q;


D_Flip_Flop DUT(.clk(clk),.rst(rst),.data(data),.q(q));

initial clk = 0;
always #5 clk = ~ clk;

initial begin 

    $dumpfile("D_Flip_Flop.vcd");
    $dumpvars(0,D_Flip_Flop_tb);
     
    for(integer i = 0 ; i<2**3 ; i = i+1) begin
        {rst,data} = $random;
        #5;
end

    #100 $finish;

end

    
endmodule

D_Flip_Flop.vcd
$date
	Fri Nov 28 11:28:51 2025
$end
$version
	Icarus Verilog
$end
$timescale
	1ps
$end
$scope module D_Flip_Flop_tb $end
$var wire 1 ! q $end
$var reg 1 " clk $end
$var reg 1 # data $end
$var reg 1 $ rst $end
$scope module DUT $end
$var wire 1 " clk $end
$var wire 1 # data $end
$var wire 1 $ rst $end
$var reg 1 ! q $end
$upscope $end
$scope begin $ivl_for_loop0 $end
$var integer 32 % i [31:0] $end
$upscope $end
$upscope $end
$enddefinitions $end
$comment Show the parameter values. $end
$dumpall
$end
#0
$dumpvars
b0 %
0$
0#
0"
x!
$end
#5
1!
1#
b1 %
1"
#10
b10 %
0"
#15
0!
1$
b11 %
1"
#20
0$
b100 %
0"
#25
1!
b101 %
1"
#30
b110 %
0"
#35
0!
1$
0#
b111 %
1"
#40
b1000 %
0"
