full_adder.v
module Full_Adder(
    input a,b,cin,
    output sum,carry

);

wire w1,c1,c2,c3,c4;

    xor(w1,a,b);   
    xor(sum,w1,cin);
    and(c1,a,b);
    and(c2,b,cin);
    and(c3,cin,a);
    or(c4,c1,c2);
    or(carry,c4,c3);
    

    endmodule

full_adder_tb.v
`timescale 1ns/1ps
`include "full_adder.v"

module Full_Adder_tb;

reg a,b,cin;
wire sum,carry;

Full_Adder uut (.a(a), .b(b), .cin(cin), .carry(carry), .sum(sum));

integer i;

initial begin
    $dumpfile("Full_Adder.vcd");
    $dumpvars(0, Full_Adder_tb);

    for(i = 0 ; i < 8 ; i = i + 1) begin
        {a,b,cin} = i;
        #10;
    end

    $finish;
end
    
endmodule

Full_Adder.vcd
$date
	Mon Nov 24 01:00:49 2025
$end
$version
	Icarus Verilog
$end
$timescale
	1ps
$end
$scope module Full_Adder_tb $end
$var wire 1 ! sum $end
$var wire 1 " carry $end
$var reg 1 # a $end
$var reg 1 $ b $end
$var reg 1 % cin $end
$var integer 32 & i [31:0] $end
$scope module uut $end
$var wire 1 # a $end
$var wire 1 $ b $end
$var wire 1 ' c1 $end
$var wire 1 ( c2 $end
$var wire 1 ) c3 $end
$var wire 1 * c4 $end
$var wire 1 " carry $end
$var wire 1 % cin $end
$var wire 1 ! sum $end
$var wire 1 + w1 $end
$upscope $end
$upscope $end
$enddefinitions $end
$comment Show the parameter values. $end
$dumpall
$end
#0
$dumpvars
0+
0*
0)
0(
0'
b0 &
0%
0$
0#
0"
0!
$end
#10000
1!
1%
b1 &
#20000
1+
1!
1$
0%
b10 &
#30000
1"
1*
0!
1(
1%
b11 &
#40000
0"
0*
1!
0(
1#
0$
0%
b100 &
#50000
1"
0!
1)
1%
b101 &
#60000
1*
1"
0+
1'
0!
0)
1$
0%
b110 &
#70000
1!
1(
1)
1%
b111 &
#80000
b1000 &
