mod_n_counter.v
module mod_n_counter #(
    parameter N = 6,  // number of counter
    parameter W = 4 // Width of bits no of flip flop
)
(
    input clk,
    input rst,
    output reg [W-1:0] q
);

always @(posedge clk or posedge rst) begin
    if(rst) q <= 0;
    else if (q == N-1)
      q <= 0;
    else
     q <= q + 1;

end

    
endmodule

mod_n_counter_tb.v
`timescale 1ns/1ps
`include "mod_n_counter.v"

module mod_n_counter_tb;
    // parameters for the testbench
    parameter N = 6; // total number of states
    parameter W = 4; // number of bits (width of q)

    reg clk;
    reg rst;
    wire [W-1:0] q;

    // Instantiate DUT with parameters (if your DUT has the same parameter names)
    mod_n_counter #(
        .N(N),
        .W(W)
    ) DUT (
        .clk(clk),
        .rst(rst),
        .q(q)
    );

    // 10 ns clock period (100 MHz)
    initial clk = 0;
    always #5 clk = ~clk;

    initial begin
        $dumpfile("mod_n_counter.vcd");
        $dumpvars(0, mod_n_counter_tb);

        // Apply reset pulse (hold for a bit more than one clock cycle)
        rst = 1;
        #12;
        rst = 0;

        // Run for enough cycles to observe counting and wrap-around
        // (each clock period is 10 ns, so (N+4)*10 gives a few extra cycles)
        #((N + 4) * 10);

        $finish;
    end
endmodule

mod_n_counter.vcd
$date
	Tue Dec 02 22:16:54 2025
$end
$version
	Icarus Verilog
$end
$timescale
	1ps
$end
$scope module mod_n_counter_tb $end
$var wire 4 ! q [3:0] $end
$var parameter 32 " N $end
$var parameter 32 # W $end
$var reg 1 $ clk $end
$var reg 1 % rst $end
$scope module DUT $end
$var wire 1 $ clk $end
$var wire 1 % rst $end
$var parameter 32 & N $end
$var parameter 32 ' W $end
$var reg 4 ( q [3:0] $end
$upscope $end
$upscope $end
$enddefinitions $end
$comment Show the parameter values. $end
$dumpall
b100 '
b110 &
b100 #
b110 "
$end
#0
$dumpvars
b0 (
1%
0$
b0 !
$end
#5000
1$
#10000
0$
#12000
0%
#15000
b1 !
b1 (
1$
#20000
0$
#25000
b10 !
b10 (
1$
#30000
0$
#35000
b11 !
b11 (
1$
#40000
0$
#45000
b100 !
b100 (
1$
#50000
0$
#55000
b101 !
b101 (
1$
#60000
0$
#65000
b0 !
b0 (
1$
#70000
0$
#75000
b1 !
b1 (
1$
#80000
0$
#85000
b10 !
b10 (
1$
#90000
0$
#95000
b11 !
b11 (
1$
#100000
0$
#105000
b100 !
b100 (
1$
