Mux_2x1.v
// Gate Level Modeling Design
module Mux_2x1 (
    input [1:0]i,
    input sel,
    output y
);

wire selbar,w1,w2;

   not(selbar,sel);
   and(w1,selbar,i[0]);
   and(w2,sel,i[1]);
   or(y,w1,w2);
   

endmodule

Mux_2x1_tb.v
`timescale 1ns/1ps
`include "Mux_2x1.v"

module Mux_2x1_tb ();
reg [1:0]x;
reg Selector;
wire Y;
Mux_2x1 dut(.i(x),.sel(Selector),.y(Y));

reg clk;
always #10 clk=~clk;
initial
begin
    
    clk=0;
    $dumpfile("Mux_2x1.vcd");
    $dumpvars(0,Mux_2x1_tb);
    for(integer n = 0; n<2**3;n=n+1)begin
        {Selector,x}=n;
        #5;
    end

    //    Selector = 0 ; x[1]=0; x[0]=0;
    // #5 Selector = 0 ; x[1]=0; x[0]=1;
    // #5 Selector = 0 ; x[1]=1; x[0]=0;
    // #5 Selector = 0 ; x[1]=1; x[0]=1;
    // #5 Selector = 1 ; x[1]=0; x[0]=0;
    // #5 Selector = 1 ; x[1]=0; x[0]=1;
    // #5 Selector = 1 ; x[1]=1; x[0]=0;
    // #5 Selector = 1 ; x[1]=1; x[0]=1;

    $finish;
    
end
    
endmodule

Mux_2x1.vcd
$date
	Sat Nov 22 19:45:43 2025
$end
$version
	Icarus Verilog
$end
$timescale
	1ps
$end
$scope module Mux_2x1_tb $end
$var wire 1 ! Y $end
$var reg 1 " Selector $end
$var reg 1 # clk $end
$var reg 2 $ x [1:0] $end
$scope module dut $end
$var wire 2 % i [1:0] $end
$var wire 1 " sel $end
$var wire 1 & selbar $end
$var wire 1 ' w1 $end
$var wire 1 ( w2 $end
$var wire 1 ! y $end
$upscope $end
$scope begin $ivl_for_loop0 $end
$var integer 32 ) n [31:0] $end
$upscope $end
$upscope $end
$enddefinitions $end
$comment Show the parameter values. $end
$dumpall
$end
#0
$dumpvars
b0 )
0(
0'
1&
b0 %
b0 $
0#
0"
0!
$end
#5000
1!
1'
b1 $
b1 %
b1 )
#10000
0!
0'
b10 $
b10 %
b10 )
1#
#15000
1!
1'
b11 $
b11 %
b11 )
#20000
0!
0'
0&
1"
b0 $
b0 %
b100 )
0#
#25000
b1 $
b1 %
b101 )
#30000
1!
1(
b10 $
b10 %
b110 )
1#
#35000
b11 $
b11 %
b111 )
#40000
b1000 )
0#
