Ripple_Adder.v
module full_adder(
    input a,
    input b,
    input cin,
    output sum,
    output carry
);

  assign sum = a ^ b ^ cin;
  assign carry = a & b | b & cin | cin & a;
    
endmodule

module Ripple_Adder(
 input wire [3:0] a,
 input wire [3:0] b,
 input wire cin,
 output cout,
 output [3:0] sum
);

wire w1, w2, w3;
full_adder f0(.a(a[0]), .b(b[0]), .cin(cin), .sum(sum[0]), .carry(w1));
full_adder f1(.a(a[1]), .b(b[1]), .cin(w1), .sum(sum[1]), .carry(w2));
full_adder f2(.a(a[2]), .b(b[2]), .cin(w2), .sum(sum[2]), .carry(w3));
full_adder f3(.a(a[3]), .b(b[3]), .cin(w3), .sum(sum[3]), .carry(cout));

endmodule

Ripple_Adder_tb.v
`timescale 1ns/1ps
`include "Ripple_adder.v"

module Ripple_Adder_tb();
reg [3:0] a;
reg [3:0] b;
reg cin;
wire cout;
wire [3:0] sum;

Ripple_Adder dut (.a(a), .b(b), .cout(cout), .sum(sum), .cin(cin));

initial begin
    $dumpfile("Ripple_Adder.vcd");
    $dumpvars(0, Ripple_Adder_tb);

    for (integer i = 0; i < 2**4; i = i + 1) begin
        {a, b, cin} = i;
        #10;
    end

    $finish;
end

initial begin
    $monitor("Time=%0t | A=%b | B=%b | cin=%b | cout=%b | sum=%b", 
             $time, a, b, cin, cout, sum);
end

endmodule

Ripple_Adder.vcd
$date
	Thu Nov 27 01:08:43 2025
$end
$version
	Icarus Verilog
$end
$timescale
	1ps
$end
$scope module Ripple_Adder_tb $end
$var wire 4 ! sum [3:0] $end
$var wire 1 " cout $end
$var reg 4 # a [3:0] $end
$var reg 4 $ b [3:0] $end
$var reg 1 % cin $end
$scope module dut $end
$var wire 4 & a [3:0] $end
$var wire 4 ' b [3:0] $end
$var wire 1 % cin $end
$var wire 1 ( w3 $end
$var wire 1 ) w2 $end
$var wire 1 * w1 $end
$var wire 4 + sum [3:0] $end
$var wire 1 " cout $end
$scope module f0 $end
$var wire 1 , a $end
$var wire 1 - b $end
$var wire 1 * carry $end
$var wire 1 % cin $end
$var wire 1 . sum $end
$upscope $end
$scope module f1 $end
$var wire 1 / a $end
$var wire 1 0 b $end
$var wire 1 ) carry $end
$var wire 1 * cin $end
$var wire 1 1 sum $end
$upscope $end
$scope module f2 $end
$var wire 1 2 a $end
$var wire 1 3 b $end
$var wire 1 ( carry $end
$var wire 1 ) cin $end
$var wire 1 4 sum $end
$upscope $end
$scope module f3 $end
$var wire 1 5 a $end
$var wire 1 6 b $end
$var wire 1 " carry $end
$var wire 1 ( cin $end
$var wire 1 7 sum $end
$upscope $end
$upscope $end
$scope begin $ivl_for_loop0 $end
$var integer 32 8 i [31:0] $end
$upscope $end
$upscope $end
$enddefinitions $end
$comment Show the parameter values. $end
$dumpall
$end
#0
$dumpvars
b0 8
07
06
05
04
03
02
01
00
0/
0.
0-
0,
b0 +
0*
0)
0(
b0 '
b0 &
0%
b0 $
b0 #
0"
b0 !
$end
#10000
b1 !
b1 +
1.
1%
b1 8
#20000
1-
b1 !
b1 +
1.
b1 $
b1 '
0%
b10 8
#30000
11
1*
b10 !
b10 +
0.
1%
b11 8
#40000
04
0)
0*
0-
10
b10 !
b10 +
0.
b10 $
b10 '
0%
b100 8
#50000
b11 !
b11 +
1.
1%
b101 8
#60000
1-
b11 !
b11 +
1.
b11 $
b11 '
0%
b110 8
#70000
14
1)
01
1*
b100 !
b100 +
0.
1%
b111 8
#80000
07
0)
0(
14
0*
0-
00
13
b100 !
b100 +
0.
b100 $
b100 '
0%
b1000 8
#90000
b101 !
b101 +
1.
1%
b1001 8
#100000
1-
b101 !
b101 +
1.
b101 $
b101 '
0%
b1010 8
#110000
11
1*
b110 !
b110 +
0.
1%
b1011 8
#120000
07
0(
14
0)
0*
0-
10
b110 !
b110 +
0.
b110 $
b110 '
0%
b1100 8
#130000
b111 !
b111 +
1.
1%
b1101 8
#140000
1-
b111 !
b111 +
1.
b111 $
b111 '
0%
b1110 8
#150000
17
1(
04
1)
01
1*
b1000 !
b1000 +
0.
1%
b1111 8
#160000
b10000 8
