S_R_Flip_Flop.v
module S_R_Flip_Flop(
    input S,    // set input 
    input R,    // Reset Input
    input clk,  // Clock 
    input rst,  // System Reset
    output reg q  // Output 
);

always @(posedge clk) begin    // psotive edage triggered 
    if(rst)                    // reset is high
    q <= 1'b0;                 //   q is zero 
    else begin
    case({S,R})
      2'b00 : q <= q;          // Data is same 
      2'b01 : q <= 1'b0;       //  again zero
      2'b10 : q <= 1'b1;       //  again 1 
      2'b11 : q <= 1'bz;       // high impedence
      default : q <= 1'bx;

    endcase
    end
end
    
endmodule

S_R_Flip_Flop_tb.v
// ...existing code...
`timescale 1ps/1ps
`include "S_R_Flip_Flop.v"

module S_R_Flip_Flop_tb();
reg S, R, clk, rst;
wire q;

S_R_Flip_Flop dut (.S(S), .R(R), .clk(clk), .q(q));

initial clk = 0;
always #5 clk = ~clk;

initial begin 
    $dumpfile("S_R_Flip_Flop.vcd");
    $dumpvars(0, S_R_Flip_Flop_tb);
    #10
     rst = 1;
     #10 rst = 0;
     #10 S = 0; R = 0;
     #10 S = 0; R = 1;
     #10 S = 1; R = 0;
     #10 S = 1; R = 1;
  #100 $finish;
    end 

    
endmodule

S_R_Flip_Flop.vcd
$date
	Sat Nov 29 00:43:00 2025
$end
$version
	Icarus Verilog
$end
$timescale
	1ps
$end
$scope module S_R_Flip_Flop_tb $end
$var wire 1 ! q $end
$var reg 1 " R $end
$var reg 1 # S $end
$var reg 1 $ clk $end
$var reg 1 % rst $end
$scope module dut $end
$var wire 1 " R $end
$var wire 1 # S $end
$var wire 1 $ clk $end
$var wire 1 & rst $end
$var reg 1 ! q $end
$upscope $end
$upscope $end
$enddefinitions $end
$comment Show the parameter values. $end
$dumpall
$end
#0
$dumpvars
z&
x%
0$
x#
x"
x!
$end
#5
1$
#10
0$
1%
#15
1$
#20
0$
0%
#25
1$
#30
0$
0"
0#
#35
1$
#40
0$
1"
#45
0!
1$
#50
0$
0"
1#
#55
1!
1$
#60
0$
1"
#65
z!
1$
