seq_det_non_overlap.v
module seq_dect_1010 (input clk , input rst , input data_in, output reg out );
parameter S0 = 4'h1;
parameter S1 = 4'h2;
parameter S2 = 4'h3;
parameter S3 = 4'h4;
parameter S4 = 4'h5;

reg [3:0] state, next_state;

always @(posedge clk or negedge rst ) begin  // this is for check states only 
    if(!rst)
       state = S0;
    else
       state <= next_state;
end

always @(state or data_in) begin
    case(state)
    S0: begin if(data_in == 0 ) next_state = S0;
    else next_state = S1; end
    S1: begin if(data_in == 0) next_state = S2;
        else next_state = S1; end
    S2: begin if(data_in == 0) next_state = S0;
    else next_state = S3; end
    S3: begin if(data_in == 0 ) next_state = S4;
    else next_state = S1; end
    S4: begin if(data_in == 0 ) next_state = S0;
    else next_state = S1; end
    default : next_state = S0;

    endcase
end

always @(state) begin
    case(state)
    S0: out = 0;
    S1: out = 0;
    S2: out = 0;
    S3: out = 0;
    S4: out = 1;
    default : out = 0;
     endcase
end
endmodule

seq_det_non_overlap_tb.v
`timescale 1ns/1ps
`include "seq_det_non_overlap.v"

module seq_dect_1010_tb ();

reg clk;
reg rst;
reg data_in;
wire out;

seq_dect_1010 dut(.clk(clk),.rst(rst),.data_in(data_in),.out(out));
    
initial clk = 0;
always #5 clk = ~clk; // 100Mhz clock 

initial begin
    $dumpfile("seq_Dect_1010.vcd");
    $dumpvars(0,seq_dect_1010_tb);
    #5 data_in = 1;
    #5 rst = 0;
    #5 rst = 1;
    #10 data_in = 0;
    #10 data_in = 1;
    #10 data_in = 0;
    #10 data_in = 1;
    #10 data_in = 1;
    #10 data_in = 0;
    #10 data_in = 0;
    #10 data_in = 0;
    #10 data_in = 1;
    #10 data_in = 0;
    #10 data_in = 1;
    #10 data_in = 0;
    #10 data_in = 1;
    #10 data_in = 0;

    #300 $finish;

end
endmodule

seq_Dect_1010.vcd
$date
	Thu Dec 04 00:36:27 2025
$end
$version
	Icarus Verilog
$end
$timescale
	1ps
$end
$scope module seq_dect_1010_tb $end
$var wire 1 ! out $end
$var reg 1 " clk $end
$var reg 1 # data_in $end
$var reg 1 $ rst $end
$scope module dut $end
$var wire 1 " clk $end
$var wire 1 # data_in $end
$var wire 1 $ rst $end
$var parameter 4 % S0 $end
$var parameter 4 & S1 $end
$var parameter 4 ' S2 $end
$var parameter 4 ( S3 $end
$var parameter 4 ) S4 $end
$var reg 4 * next_state [3:0] $end
$var reg 1 ! out $end
$var reg 4 + state [3:0] $end
$upscope $end
$upscope $end
$enddefinitions $end
$comment Show the parameter values. $end
$dumpall
b101 )
b100 (
b11 '
b10 &
b1 %
$end
#0
$dumpvars
bx +
bx *
x$
x#
0"
x!
$end
#5000
b1 *
1#
1"
#10000
0!
b10 *
b1 +
0$
0"
#15000
b10 +
1$
1"
#20000
0"
#25000
b11 +
b1 *
1"
0#
#30000
0"
#35000
b100 +
b10 *
1"
1#
#40000
0"
#45000
1!
b101 +
b1 *
1"
0#
#50000
0"
#55000
0!
b10 +
b10 *
1"
1#
#60000
0"
#65000
1"
#70000
0"
#75000
b11 +
b1 *
1"
0#
#80000
0"
#85000
b1 +
1"
#90000
0"
#95000
1"
#100000
0"
#105000
b10 +
b10 *
1"
1#
#110000
0"
#115000
b11 +
b1 *
1"
0#
#120000
0"
#125000
b100 +
b10 *
1"
1#
#130000
0"
#135000
1!
b101 +
b1 *
1"
0#
#140000
0"
#145000
0!
b10 +
b10 *
1"
1#
#150000
0"
#155000
b11 +
b1 *
1"
0#
#160000
0"
#165000
b1 +
1"
