TLC.v
module TLC (
    input clk,
    output reg [0:2] light
);

parameter S0 = 0; parameter S1 = 1; parameter S2 = 2;
parameter RED = 3'b100 , GREEN = 3'b010 ,YELLOW = 3'b001;
reg [0:1] states;

always @(posedge clk) begin
    case(states)
    S0 : states <= S1;
    S1 : states <= S2;
    S2 : states <= S0;
    default : states <= S0;

    endcase

end

always @(states) begin
    case(states)
    S0 : light = RED;
    S1 : light = YELLOW;
    S2 : light = GREEN;
    default : states = RED;
    endcase
end

    
endmodule

TLC_tb.v
`timescale 1ns/1ps
`include "TLC.v"
module TLC_tb ();
    reg clk;
    wire [0:2] light;


TLC DUT(.clk(clk),.light(light));

initial clk = 0;
always #5 clk = ~clk;   // 100 Mhz clock 

initial begin 
    $dumpfile("TLC.vcd");
    $dumpvars(0,TLC_tb);

    #100 $finish;

end

endmodule

TLC.vcd
$date
	Wed Dec 03 21:18:50 2025
$end
$version
	Icarus Verilog
$end
$timescale
	1ps
$end
$scope module TLC_tb $end
$var wire 3 ! light [0:2] $end
$var reg 1 " clk $end
$scope module DUT $end
$var wire 1 " clk $end
$var parameter 3 # GREEN $end
$var parameter 3 $ RED $end
$var parameter 32 % S0 $end
$var parameter 32 & S1 $end
$var parameter 32 ' S2 $end
$var parameter 3 ( YELLOW $end
$var reg 3 ) light [0:2] $end
$var reg 2 * states [0:1] $end
$upscope $end
$upscope $end
$enddefinitions $end
$comment Show the parameter values. $end
$dumpall
b1 (
b10 '
b1 &
b0 %
b100 $
b10 #
$end
#0
$dumpvars
bx *
bx )
0"
bx !
$end
#5000
b100 !
b100 )
b0 *
1"
#10000
0"
#15000
b1 !
b1 )
b1 *
1"
#20000
0"
#25000
b10 !
b10 )
b10 *
1"
#30000
0"
#35000
b100 !
b100 )
b0 *
1"
#40000
0"
#45000
b1 !
b1 )
b1 *
1"
#50000
0"
#55000
b10 !
b10 )
b10 *
1"
#60000
0"
#65000
b100 !
b100 )
b0 *
1"
#70000
0"
#75000
b1 !
b1 )
b1 *
1"
#80000
0"
#85000
b10 !
b10 )
b10 *
1"
#90000
0"
#95000
b100 !
b100 )
b0 *
1"
#100000
0"
#105000
b1 !
b1 )
b1 *
1"
#110000
0"
#115000
b10 !
b10 )
b10 *
1"
#120000
0"
#125000
b100 !
b100 )
b0 *
1"
#130000
0"
#135000
b1 !
b1 )
b1 *
1"
#140000
0"
#145000
b10 !
b10 )
b10 *
1"
